BootIntegrityValidator/__init__.py
BootIntegrityValidator/package_meta_data.py
BootIntegrityValidator/platforms.py
BootIntegrityValidator/certs/ACT2SUDICA.pem
BootIntegrityValidator/certs/Known_Good_Values_PROD.pem
BootIntegrityValidator/certs/README.txt
BootIntegrityValidator/certs/crca2048.pem
BootIntegrityValidator/certs/crca2099.pem
BootIntegrityValidator/certs/crcam2.pem
BootIntegrityValidator/certs/hasudi.pem
BootIntegrityValidator/certs/innerspace.cer
BootIntegrityValidator/yang/Cisco-IOS-XE-common-types.yang
BootIntegrityValidator/yang/Cisco-IOS-XE-system-integrity-oper.yang
BootIntegrityValidator/yang/__init__.py
BootIntegrityValidator/yang/cisco-semver.yang
BootIntegrityValidator-2.2.1.dist-info/LICENSE
BootIntegrityValidator-2.2.1.dist-info/METADATA
BootIntegrityValidator-2.2.1.dist-info/WHEEL
BootIntegrityValidator-2.2.1.dist-info/top_level.txt
BootIntegrityValidator-2.2.1.dist-info/RECORD
