Metadata-Version: 2.1
Name: BootIntegrityValidator
Version: 2.2.1
Summary: A Python module to validate the Boot Integrity Visibility Output in Cisco Products.
Home-page: https://github.com/CiscoDevNet/BootIntegrityValidator
Author: Jay Young
Author-email: jyoungta@cisco.com
License: UNKNOWN
Platform: UNKNOWN
Classifier: Development Status :: 4 - Beta
Classifier: Programming Language :: Python :: 2
Classifier: Programming Language :: Python :: 3
Classifier: Topic :: Security :: Cryptography
License-File: LICENSE
Requires-Dist: pyOpenSSL
Requires-Dist: pycryptodome
Requires-Dist: cffi
Requires-Dist: setuptools
